one_relator_curvature/__init__.py
one_relator_curvature/analysis.py
one_relator_curvature/cell_complex.py
one_relator_curvature/circle_intersection.py
one_relator_curvature/classifier.py
one_relator_curvature/cli_functions.py
one_relator_curvature/clustering.py
one_relator_curvature/constants.py
one_relator_curvature/database.py
one_relator_curvature/decorators.py
one_relator_curvature/display.py
one_relator_curvature/errors.py
one_relator_curvature/example.py
one_relator_curvature/hyperbolic_plane.py
one_relator_curvature/important_examples.py
one_relator_curvature/main.py
one_relator_curvature/parsers.py
one_relator_curvature/plotting.py
one_relator_curvature/punctured_surfaces.py
one_relator_curvature/start.py
one_relator_curvature/tables.py
one_relator_curvature/utils.py
one_relator_curvature/word.py
one_relator_curvature/word_generator.py
one_relator_curvature/word_utils.py
one_relator_curvature-0.3.3.dist-info/LICENSE
one_relator_curvature-0.3.3.dist-info/METADATA
one_relator_curvature-0.3.3.dist-info/WHEEL
one_relator_curvature-0.3.3.dist-info/entry_points.txt
one_relator_curvature-0.3.3.dist-info/top_level.txt
one_relator_curvature-0.3.3.dist-info/RECORD
