Metadata-Version: 2.1
Name: one-relator-curvature
Version: 0.3.3
Summary: A package for studying regular sectional curvature of one relator groups
Home-page: https://github.com/antonydellavecchia/one_relator_curvature
Author: Antony Della Vecchia
Author-email: antonydellavecchia@gmail.com
License: UNKNOWN
Platform: UNKNOWN
Classifier: Programming Language :: Python :: 3
Classifier: License :: OSI Approved :: MIT License
Classifier: Operating System :: OS Independent
Requires-Python: >=3.6
Requires-Dist: matplotlib
Requires-Dist: mpmath
Requires-Dist: sqlalchemy
Requires-Dist: pulp
Requires-Dist: networkx
Requires-Dist: cplex
